{
		"questions" :[
			{"question":"2+2=4","answer":"x","mode":"INTRODUCTION_MODE"},
			{"question":"3+3=6","answer":"x","mode":"INTRODUCTION_MODE"},
			{"question":"4+4=8","answer":"x","mode":"INTRODUCTION_MODE"},
			{"question":"2+2=","answer":"4","mode":"ENGRAVE_MODE"},
			{"question":"3+3=","answer":"6","mode":"ENGRAVE_MODE"},
			{"question":"4+4=","answer":"8","mode":"ENGRAVE_MODE"},
			{"question":"2+2=","answer":"4","mode":"CHECK_MODE"},
			{"question":"3+3=","answer":"6","mode":"CHECK_MODE"},
			{"question":"4+4=","answer":"8","mode":"CHECK_MODE"}
			]
}